README.md
setup.py
sdi_utils/__init__.py
sdi_utils/call_proc.py
sdi_utils/gensolution.py
sdi_utils/outputgen.py
sdi_utils/textfield_parser.py
sdi_utils/tprogress.py
sdi_utils.egg-info/PKG-INFO
sdi_utils.egg-info/PKG-INFO-C02Z82A3LVDM
sdi_utils.egg-info/SOURCES-C02Z82A3LVDM.txt
sdi_utils.egg-info/SOURCES.txt
sdi_utils.egg-info/dependency_links.txt
sdi_utils.egg-info/entry_points.txt
sdi_utils.egg-info/requires.txt
sdi_utils.egg-info/top_level.txt
solution/__init__.py
src/__init__.py
src/sdi_utils_operators/__init__.py
src/sdi_utils_operators/HTTPdownload/HTTPdownload.py
src/sdi_utils_operators/HTTPdownload/__init__.py
src/sdi_utils_operators/csv_df/__init__.py
src/sdi_utils_operators/csv_df/csv_df.py
src/sdi_utils_operators/csv_dict/__init__.py
src/sdi_utils_operators/csv_dict/csv_dict.py
src/sdi_utils_operators/csv_table_create/__init__.py
src/sdi_utils_operators/csv_table_create/csv_table_create.py
src/sdi_utils_operators/decision/__init__.py
src/sdi_utils_operators/decision/decision.py
src/sdi_utils_operators/df_csv/__init__.py
src/sdi_utils_operators/df_csv/df_csv.py
src/sdi_utils_operators/df_json/__init__.py
src/sdi_utils_operators/df_json/df_json.py
src/sdi_utils_operators/df_replication_cols/__init__.py
src/sdi_utils_operators/df_replication_cols/df_replication_cols.py
src/sdi_utils_operators/dict_df/__init__.py
src/sdi_utils_operators/dict_df/dict_df.py
src/sdi_utils_operators/dict_json/__init__.py
src/sdi_utils_operators/dict_json/dict_json.py
src/sdi_utils_operators/drop_duplicates/__init__.py
src/sdi_utils_operators/drop_duplicates/drop_duplicates.py
src/sdi_utils_operators/filter_date/__init__.py
src/sdi_utils_operators/filter_date/filter_date.py
src/sdi_utils_operators/gate/__init__.py
src/sdi_utils_operators/gate/gate.py
src/sdi_utils_operators/json_df/__init__.py
src/sdi_utils_operators/json_df/json_df.py
src/sdi_utils_operators/json_dict/__init__.py
src/sdi_utils_operators/json_dict/json_dict.py
src/sdi_utils_operators/line_array/__init__.py
src/sdi_utils_operators/line_array/line_array.py
src/sdi_utils_operators/merge_attributes/__init__.py
src/sdi_utils_operators/merge_attributes/merge_attributes.py
src/sdi_utils_operators/pandas_script/__init__.py
src/sdi_utils_operators/pandas_script/pandas_script.py
