Metadata-Version: 2.1
Name: sdi-utils
Version: 0.0.88
Summary: List of SAP DI helper functions like gensolution (package locally developed operators,textfield_parser, time_monitoring
Home-page: https://github.com/thhapke/gensolution
Author: Thorsten Hapke
Author-email: thorsten.hapke@sap.com
License: UNKNOWN
Keywords: SAP Data Intelligence,genjson,tprogress,textfield_parser
Platform: UNKNOWN
Classifier: Programming Language :: Python :: 3.5
Classifier: Programming Language :: Python :: 3.6
Classifier: Programming Language :: Python :: 3.7
Classifier: Programming Language :: Python :: 3.8
Classifier: License :: OSI Approved :: MIT License
Classifier: Operating System :: OS Independent
